MANIFEST.in
requirements.txt
setup.py
../CHANGELOG.md
../LICENSE.txt
../README.md
rekono/__init__.py
rekono/main.py
rekono/client/__init__.py
rekono/client/api.py
rekono/client/enums.py
rekono/client/exceptions.py
rekono/commands/__init__.py
rekono/commands/api.py
rekono/commands/authentications.py
rekono/commands/configurations.py
rekono/commands/executions.py
rekono/commands/findings.py
rekono/commands/processes.py
rekono/commands/profile.py
rekono/commands/projects.py
rekono/commands/settings.py
rekono/commands/steps.py
rekono/commands/target_ports.py
rekono/commands/targets.py
rekono/commands/tasks.py
rekono/commands/tools.py
rekono/commands/users.py
rekono/commands/wordlists.py
rekono/framework/__init__.py
rekono/framework/arguments.py
rekono/framework/options.py
rekono/framework/commands/__init__.py
rekono/framework/commands/api.py
rekono/framework/commands/command.py
rekono/framework/commands/entity.py
rekono_cli.egg-info/PKG-INFO
rekono_cli.egg-info/SOURCES.txt
rekono_cli.egg-info/dependency_links.txt
rekono_cli.egg-info/entry_points.txt
rekono_cli.egg-info/requires.txt
rekono_cli.egg-info/top_level.txt