Metadata-Version: 2.1
Name: rekono-cli
Version: 2.0.1.post1
Summary: CLI to make requests to Rekono API
Home-page: https://github.com/pablosnt/rekono-cli
Author: Pablo Santiago López
License: UNKNOWN
Project-URL: Rekono, https://github.com/pablosnt/rekono
Project-URL: Rekono CLI, https://github.com/pablosnt/rekono-cli
Keywords: automation,pentesting,security,cli,rekono
Platform: UNKNOWN
Requires-Python: >=3.7
